benyo_zbx/__init__.py
benyo_zbx/lib/__init__.py
benyo_zbx/lib/alert.py
benyo_zbx/lib/base.py
benyo_zbx/lib/event.py
benyo_zbx/lib/host.py
benyo_zbx/lib/item.py
benyo_zbx/lib/trigger.py
benyo_zbx-1.0.0.dist-info/LICENSE
benyo_zbx-1.0.0.dist-info/METADATA
benyo_zbx-1.0.0.dist-info/WHEEL
benyo_zbx-1.0.0.dist-info/top_level.txt
benyo_zbx-1.0.0.dist-info/RECORD
